Aziiz/__init__.py
AziizAM-0.0.4.dist-info/LICENCE.txt
AziizAM-0.0.4.dist-info/METADATA
AziizAM-0.0.4.dist-info/WHEEL
AziizAM-0.0.4.dist-info/top_level.txt
AziizAM-0.0.4.dist-info/RECORD
