Metadata-Version: 2.1
Name: AziizAM
Version: 0.0.4
Summary: Fast way to access my custom python function.
Home-page: https://github.com/AziizMq/AziizAM-Pypi
Author: A.Alminqah
Author-email: A.Alminqah@hotmail.com
Project-URL: Tracker, https://github.com/AziizMq/AziizAM-Pypi/issues
Classifier: Programming Language :: Python :: 3
Classifier: License :: OSI Approved :: MIT License
Classifier: Operating System :: OS Independent
License-File: LICENCE.txt
